blob.py
db.py
givvableutils-0.0.5.dist-info/LICENSE
givvableutils-0.0.5.dist-info/METADATA
givvableutils-0.0.5.dist-info/WHEEL
givvableutils-0.0.5.dist-info/top_level.txt
givvableutils-0.0.5.dist-info/RECORD
